LICENSE
MANIFEST.in
README
setup.py
src/main
src/Midterm.egg-info/PKG-INFO
src/Midterm.egg-info/SOURCES.txt
src/Midterm.egg-info/dependency_links.txt
src/Midterm.egg-info/requires.txt
src/Midterm.egg-info/top_level.txt
src/myMidterm/__init__.py
src/myMidterm/match.py
src/myMidterm/write.py