Metadata-Version: 1.1
Name: Midterm
Version: 0.1
Summary: Programming Languages Mid-Term
Home-page: UNKNOWN
Author: Edsel Norwood
Author-email: ebnorwood538@students.ecsu.edu
License: Creative Commons Attribution-Noncommercial-Share Alike license
Platform: UNKNOWN
Classifier: Development Status :: 4 - Beta
Classifier: Environment :: X11 Applications :: GTK
Classifier: Intended Audience :: End Users/Desktop
Classifier: Intended Audience :: Developers
Classifier: License :: OSI Approved :: GNU General Public License (GPL)
Classifier: Operating System :: POSIX :: Linux
Classifier: Programming Language :: Python
Classifier: Topic :: Desktop Environment
Classifier: Topic :: Text Processing :: Fonts
